proconfig/__init__.py
proconfig/__version__.py
proconfig/cli.py
proconfig/graph.py
proconfig-0.1.7.dist-info/METADATA
proconfig-0.1.7.dist-info/WHEEL
proconfig-0.1.7.dist-info/entry_points.txt
proconfig-0.1.7.dist-info/top_level.txt
proconfig-0.1.7.dist-info/RECORD
