Metadata-Version: 2.1
Name: proconfig
Version: 0.1.7
Summary: A CLI tool for simplify MyShell PorConfig programming.
Home-page: https://github.com/cybernagle/proconfig-generator
Author: cybernagle
Author-email: zhang.nagle@gmail.com
Classifier: Programming Language :: Python :: 3
Classifier: License :: OSI Approved :: MIT License
Classifier: Operating System :: OS Independent
Requires-Python: >=3.6
Requires-Dist: click
Requires-Dist: tabulate
Requires-Dist: termcolor
Requires-Dist: jsonschema
Requires-Dist: dash
Requires-Dist: dash-cytoscape
